fedora_checksum_tester.py
fedora_checksum_tester-1.3.dist-info/LICENSE
fedora_checksum_tester-1.3.dist-info/METADATA
fedora_checksum_tester-1.3.dist-info/WHEEL
fedora_checksum_tester-1.3.dist-info/entry_points.txt
fedora_checksum_tester-1.3.dist-info/top_level.txt
fedora_checksum_tester-1.3.dist-info/RECORD
