Metadata-Version: 2.1
Name: fedora-checksum-tester
Version: 1.3
Summary: Image checksum tester for Fedora
Home-page: https://github.com/lruzicka/checksum-tester
Author: Lukáš Růžička
Author-email: lruzicka@redhat.com
License: UNKNOWN
Platform: UNKNOWN
Classifier: Programming Language :: Python :: 3
Classifier: License :: OSI Approved :: GNU General Public License v3 or later (GPLv3+)
Classifier: Operating System :: OS Independent
Requires-Dist: wget
Requires-Dist: fedfind
Requires-Dist: wikitcms
